music_syn/__init__.py
music_syn/demo.py
music_syn/demosongs.py
music_syn/example.py
music_syn/menv.py
music_syn/mixfiles.py
music_syn/mkfreq.py
music_syn/nokiacomposer2wav.py
music_syn/play_wav.py
music_syn/pysynth.py
music_syn/pysynth_b.py
music_syn/pysynth_beeper.py
music_syn/pysynth_c.py
music_syn/pysynth_d.py
music_syn/pysynth_e.py
music_syn/pysynth_p.py
music_syn/pysynth_s.py
music_syn/pysynth_samp.py
music_syn/read_abc.py
music_syn/readmidi.py
music_syn/test_nokiacomposer2wav.py
music_syn-2.4.dist-info/METADATA
music_syn-2.4.dist-info/WHEEL
music_syn-2.4.dist-info/top_level.txt
music_syn-2.4.dist-info/RECORD
