Metadata-Version: 2.1
Name: music-syn
Version: 2.4
Summary: A simple music synthesizer for Python 3
Home-page: http://mdoege.github.io/PySynth/
Author: Martin C. Doege
Author-email: mdoege@compuserve.com
License: UNKNOWN
Platform: UNKNOWN
Requires-Dist: numpy
Requires-Dist: pyglet
